bluepymm/__init__.py
bluepymm/main.py
bluepymm/tools.py
bluepymm/legacy/__init__.py
bluepymm/legacy/create_hoc_files.py
bluepymm/prepare_combos/__init__.py
bluepymm/prepare_combos/create_mm_sqlite.py
bluepymm/prepare_combos/main.py
bluepymm/prepare_combos/parse_files.py
bluepymm/prepare_combos/prepare_emodel_dirs.py
bluepymm/run_combos/__init__.py
bluepymm/run_combos/calculate_scores.py
bluepymm/run_combos/main.py
bluepymm/select_combos/__init__.py
bluepymm/select_combos/main.py
bluepymm/select_combos/megate_output.py
bluepymm/select_combos/process_megate_config.py
bluepymm/select_combos/reporting.py
bluepymm/select_combos/sqlite_io.py
bluepymm/select_combos/table_processing.py
bluepymm/templates/cell_template_neurodamus.jinja2
bluepymm/templates/cell_template_neurodamus_sbo.jinja2
bluepymm/templates/cell_template_neuron.jinja2
bluepymm/validate_output/__init__.py
bluepymm/validate_output/main.py
docs/.gitignore
docs/Makefile
docs/source/.gitignore
docs/source/bluepymm.prepare_combos.rst
docs/source/bluepymm.rst
docs/source/bluepymm.run_combos.rst
docs/source/bluepymm.select_combos.rst
docs/source/conf.py
docs/source/index.rst
docs/source/logo/BluePyMMBanner.png
tests/examples/cmvd3a/circuit_intlayers.mvd3
tests/examples/cmvd3a/circuit_strlayers.mvd3
tests/examples/simple1/.gitignore
tests/examples/simple1/build_git.py
tests/examples/simple1/cell_template.jinja2
tests/examples/simple1/cell_template_neuron.jinja2
tests/examples/simple1/simple1_conf_hoc.json
tests/examples/simple1/simple1_conf_prepare.json
tests/examples/simple1/simple1_conf_prepare_git.json
tests/examples/simple1/simple1_conf_run.json
tests/examples/simple1/simple1_conf_select.json
tests/examples/simple1/simple1_conf_select_2.json
tests/examples/simple1/data/simple1_recipe.xml
tests/examples/simple1/data/simple1_recipe.yaml
tests/examples/simple1/data/emodels_dir/subdir/.gitignore
tests/examples/simple1/data/emodels_dir/subdir/__init__.py
bluepymm-0.9.11.dist-info/AUTHORS.txt
bluepymm-0.9.11.dist-info/COPYING
bluepymm-0.9.11.dist-info/COPYING.lesser
bluepymm-0.9.11.dist-info/LICENSE.txt
bluepymm-0.9.11.dist-info/METADATA
bluepymm-0.9.11.dist-info/WHEEL
bluepymm-0.9.11.dist-info/entry_points.txt
bluepymm-0.9.11.dist-info/top_level.txt
bluepymm-0.9.11.dist-info/RECORD
