Metadata-Version: 2.1
Name: bluepymm
Version: 0.9.11
Summary: Model Management Python Library (bluepymm)
Author-email: "Blue Brain Project, EPFL" <werner.vangeit@epfl.ch>
License: BluePyMM - Bluebrain Python Optimisation Library
Project-URL: Homepage, https://github.com/BlueBrain/BluePyMM
Project-URL: Source, https://github.com/BlueBrain/BluePyMM
Project-URL: Repository, https://github.com/BlueBrain/BluePyMM.git
Project-URL: Tracker, https://github.com/BlueBrain/BluePyMM/issues
Project-URL: Documentation, https://bluepymm.readthedocs.io/en/latest
Keywords: optimisation,neuroscience,BlueBrainProject
Classifier: Development Status :: 4 - Beta
Classifier: Environment :: Console
Classifier: Programming Language :: Python :: 3
Classifier: Operating System :: POSIX
Classifier: Topic :: Scientific/Engineering
Classifier: Topic :: Utilities
Classifier: License :: OSI Approved :: GNU Lesser General Public License v3 (LGPLv3)
Requires-Python: >=3.9
License-File: LICENSE.txt
License-File: COPYING
License-File: COPYING.lesser
License-File: AUTHORS.txt
Requires-Dist: sh
Requires-Dist: bluepyopt
Requires-Dist: matplotlib
Requires-Dist: pandas >=2.0.0
Requires-Dist: numpy
Requires-Dist: ipyparallel
Requires-Dist: lxml
Requires-Dist: h5py
Requires-Dist: pyyaml
